{
  "generator-jhipster": {
    "promptValues": {
      "packageName": "com.app"
    },
    "jhipsterVersion": "6.5.1",
    "applicationType": "monolith",
    "baseName": "travail",
    "packageName": "com.app",
    "packageFolder": "com/app",
    "serverPort": "8080",
    "authenticationType": "jwt",
    "cacheProvider": "ehcache",
    "enableHibernateCache": false,
    "websocket": false,
    "databaseType": "sql",
    "devDatabaseType": "mysql",
    "prodDatabaseType": "mysql",
    "searchEngine": false,
    "messageBroker": false,
    "serviceDiscoveryType": "eureka",
    "buildTool": "maven",
    "enableSwaggerCodegen": false,
    "jwtSecretKey": "N2EyYzlmNzg5NjdiMTdiMjcxYTFmOWU0MGVhNjY2OTA1ZTAzZGIwMGYwMThiYTIxZjkwYzY3MzQwMzcxNDM4NzMxNjkxZmJlMWJiYTc4ODNmNjU3OWVlNGYwZTAyNzQ0OWYxMGNjMGZhOGRjZmViZDZmZTllYTE1ZjU2OTBkMzQ=",
    "embeddableLaunchScript": false,
    "useSass": true,
    "clientPackageManager": "npm",
    "clientFramework": "angularX",
    "clientTheme": "none",
    "clientThemeVariant": "",
    "testFrameworks": [],
    "jhiPrefix": "jhi",
    "entitySuffix": "",
    "dtoSuffix": "DTO",
    "otherModules": [],
    "enableTranslation": false,
    "blueprints": []
  }
}
